{
	"format_version": "1.8.0",
	"animations": {
		"idle": {
			"loop": true,
			"animation_length": 4,
			"bones": {
				"torso1": {
					"rotation": {
						"vector": ["Math.sin(query.anim_time*90)*5", 0, 0]
					}
				},
				"torso2": {
					"rotation": {
						"vector": ["Math.sin(query.anim_time*90)*-10", 0, 0]
					}
				},
				"belt": {
					"rotation": {
						"vector": [-40, 0, 0]
					},
					"position": {
						"vector": [0, 0.2, 0]
					}
				},
				"body": {
					"rotation": {
						"vector": [5, 0, 0]
					},
					"position": {
						"vector": [0, "-2.5+Math.sin(query.anim_time*90)*0.25", -2]
					}
				},
				"head": {
					"rotation": {
						"vector": [0, 0, 0]
					}
				},
				"right_arm": {
					"rotation": {
						"vector": [21.73001, -14.41468, "-17.9509+Math.sin(query.anim_time*90)*4"]
					}
				},
				"right_arm2": {
					"rotation": {
						"vector": [-35.65893, 3.11325, 7.3674]
					}
				},
				"left_arm": {
					"rotation": {
						"vector": [21.73002, 14.41468, "17.9509-Math.sin(query.anim_time*90)*4"]
					}
				},
				"left_arm2": {
					"rotation": {
						"vector": [-35.65893, -3.11325, -7.3674]
					}
				},
				"right_leg": {
					"rotation": {
						"vector": ["-23.6984-Math.sin(query.anim_time*90)*1", 35.83157, -9.45586]
					},
					"position": {
						"vector": [0, 0, 3]
					}
				},
				"right_leg2": {
					"rotation": {
						"vector": [36.30733, -23.68984, -6.51582]
					}
				},
				"left_leg": {
					"rotation": {
						"vector": ["-23.6984-Math.sin(query.anim_time*90)*1", -35.83157, 9.45586]
					},
					"position": {
						"vector": [0, 0, 2]
					}
				},
				"left_leg2": {
					"rotation": {
						"vector": [36.30733, 23.68984, 6.51582]
					}
				},
				"left_leg3": {
					"rotation": {
						"vector": [-11.08438, -0.53562, -1.67204]
					}
				},
				"right_leg3": {
					"rotation": {
						"vector": [-11.08438, 0.53562, 1.67204]
					}
				}
			}
		},
		"sprint": {
			"loop": true,
			"animation_length": 1.3333,
			"bones": {
				"body": {
					"rotation": {
						"0.0": {
							"vector": [0, -5, 0]
						},
						"0.3333": {
							"vector": [0, 0, 0]
						},
						"0.6667": {
							"vector": [0, 5, 0]
						},
						"1.0": {
							"vector": [0, 0, 0]
						},
						"1.3333": {
							"vector": [0, -5, 0]
						}
					},
					"position": {
						"0.0": {
							"vector": [0, -3, 0]
						},
						"0.3333": {
							"vector": [0, -1, 0]
						},
						"0.6667": {
							"vector": [0, -3, 0]
						},
						"1.0": {
							"vector": [0, -1, 0]
						},
						"1.3333": {
							"vector": [0, -3, 0]
						}
					}
				},
				"right_arm": {
					"rotation": {
						"0.0": {
							"vector": [-20.89994, 1.65982, -31.26266]
						},
						"0.6667": {
							"vector": [-16.0864, 2.88673, -31.67333]
						},
						"1.3333": {
							"vector": [-20.89994, 1.65982, -31.26266]
						}
					},
					"position": {
						"0.0": {
							"vector": [0.40211, -2, -3.81047]
						},
						"0.6667": {
							"vector": [0.48926, -2, -2.81428]
						},
						"1.3333": {
							"vector": [0.40211, -2, -3.81047]
						}
					}
				},
				"right_leg": {
					"rotation": {
						"0.0": {
							"vector": [-50, 0, 0]
						},
						"0.6667": {
							"vector": [50, 0, 0]
						},
						"1.0": {
							"vector": [-45, 0, 0]
						},
						"1.3333": {
							"vector": [-50, 0, 0]
						}
					}
				},
				"left_leg": {
					"rotation": {
						"0.0": {
							"vector": [50, 0, 0]
						},
						"0.3333": {
							"vector": [-45, 0, 0]
						},
						"0.6667": {
							"vector": [-50, 0, 0]
						},
						"1.3333": {
							"vector": [50, 0, 0]
						}
					}
				},
				"left_arm": {
					"rotation": {
						"0.0": {
							"vector": [-0.13038, -4.37611, 45.35335]
						},
						"0.6667": {
							"vector": [-0.13285, -11.87609, 45.37074]
						},
						"1.3333": {
							"vector": [-0.13038, -4.37611, 45.35335]
						}
					},
					"position": {
						"0.0": {
							"vector": [-0.52294, -5, -9.96195]
						},
						"1.3333": {
							"vector": [-0.52294, -5, -9.96195]
						}
					}
				},
				"head": {
					"rotation": {
						"0.0": {
							"vector": [0, 5, 0]
						},
						"0.3333": {
							"vector": [0, 0, 0]
						},
						"0.6667": {
							"vector": [0, -5, 0]
						},
						"1.0": {
							"vector": [0, 0, 0]
						},
						"1.3333": {
							"vector": [0, 5, 0]
						}
					},
					"position": {
						"0.0": {
							"vector": [-0.78441, -3, -8.96575]
						},
						"1.3333": {
							"vector": [-0.78441, -3, -8.96575]
						}
					}
				},
				"torso": {
					"rotation": {
						"0.0": {
							"vector": [22.00206, -19.3546, -11.70092]
						},
						"1.3333": {
							"vector": [22.00206, -19.3546, -11.70092]
						}
					},
					"position": {
						"0.0": {
							"vector": [-0.69725, -3, -7.96956]
						},
						"1.3333": {
							"vector": [-0.69725, -3, -7.96956]
						}
					}
				},
				"right_arm2": {
					"rotation": {
						"0.0": {
							"vector": [0, 0, 30]
						},
						"0.6667": {
							"vector": [0, 0, 30]
						},
						"1.3333": {
							"vector": [0, 0, 30]
						}
					}
				},
				"left_arm2": {
					"rotation": {
						"0.0": {
							"vector": [-61.4428, 2.89354, 12.79928]
						},
						"1.3333": {
							"vector": [-61.4428, 2.89354, 12.79928]
						}
					}
				},
				"right_leg2": {
					"rotation": {
						"0.0": {
							"vector": [30.22733, 10.56128, 8.37306]
						},
						"0.6667": {
							"vector": [52.72733, 10.56128, 8.37306]
						},
						"1.0": {
							"vector": [42.72733, 10.56128, 8.37306]
						},
						"1.3333": {
							"vector": [30.22733, 10.56128, 8.37306]
						}
					}
				},
				"left_leg2": {
					"rotation": {
						"vector": [30, 0, 0]
					}
				}
			}
		},
		"death": {
			"loop": "hold_on_last_frame",
			"animation_length": 1,
			"bones": {
				"body_chestplate": {
					"rotation": {
						"0.0": {
							"vector": [0, -6, 0]
						},
						"0.25": {
							"vector": [0, -13.5, 0]
						},
						"0.5": {
							"vector": [0, -6, 0]
						},
						"0.75": {
							"vector": [0, -6, 0]
						},
						"1.0": {
							"vector": [0, -6, 0]
						}
					},
					"position": {
						"0.0": {
							"vector": [0, 0, 0]
						},
						"0.25": {
							"vector": [0, 0.3, 0]
						},
						"0.5": {
							"vector": [0, 0, 0]
						},
						"0.75": {
							"vector": [0, 0.3, 0]
						},
						"1.0": {
							"vector": [0, 0, 0]
						}
					}
				},
				"body_chestplate2": {
					"rotation": {
						"0.0": {
							"vector": [0, 0, 0]
						},
						"0.25": {
							"vector": [0, 0, 0]
						},
						"0.5": {
							"vector": [0, 0, 0]
						},
						"0.75": {
							"vector": [0, 5, 0]
						},
						"1.0": {
							"vector": [0, 0, 0]
						}
					}
				},
				"body_chestplate3": {
					"rotation": {
						"0.0": {
							"vector": [0, 0, 0]
						},
						"0.25": {
							"vector": [0, -5, 0]
						},
						"0.5": {
							"vector": [0, 0, 0]
						},
						"0.75": {
							"vector": [0, 2.5, 0]
						},
						"1.0": {
							"vector": [0, 0, 0]
						}
					}
				},
				"body_chestplate4": {
					"rotation": {
						"0.0": {
							"vector": [0, 0, 0]
						},
						"0.25": {
							"vector": [0, 0, 0]
						},
						"0.5": {
							"vector": [0, 0, 0]
						},
						"0.75": {
							"vector": [0, 2.5, 0]
						},
						"1.0": {
							"vector": [0, 0, 0]
						}
					}
				},
				"body_chestplate1": {
					"rotation": {
						"0.0": {
							"vector": [0, 0, 0]
						},
						"0.25": {
							"vector": [0, 2.5, 0]
						},
						"0.5": {
							"vector": [0, 0, 0]
						},
						"0.75": {
							"vector": [0, 2.5, 0]
						},
						"1.0": {
							"vector": [0, 0, 0]
						}
					}
				},
				"bone_main": {
					"rotation": {
						"0.0": {
							"vector": [0, 0, 0]
						},
						"0.0833": {
							"vector": [22.5, 0, 0]
						},
						"0.75": {
							"vector": [0, 0, 0]
						}
					},
					"position": {
						"vector": [0, 0, 0]
					}
				},
				"eyes": {
					"scale": {
						"0.0": {
							"vector": [1, 1, 1]
						},
						"0.0833": {
							"vector": [0, 0, 0]
						}
					}
				},
				"body": {
					"rotation": {
						"0.0": {
							"vector": [10, 0, 0]
						},
						"0.5": {
							"vector": [-90, 0, 0]
						}
					},
					"position": {
						"0.0": {
							"vector": [0, -0.6, 0]
						},
						"0.0833": {
							"vector": [0, -2.85, 7.67]
						},
						"0.1667": {
							"vector": [0, -5.1, 11.34]
						},
						"0.5": {
							"vector": [0, -28.1, -2]
						}
					}
				},
				"head": {
					"rotation": {
						"0.0": {
							"vector": [-10, 0, 0]
						},
						"0.0833": {
							"vector": [45, 0, 0]
						},
						"0.75": {
							"vector": [0, 0, 0]
						}
					},
					"position": {
						"0.0": {
							"vector": [0, -0.5, 0]
						},
						"0.0833": {
							"vector": [0, -0.5, -5]
						},
						"0.75": {
							"vector": [0, -0.5, -3]
						}
					}
				},
				"torso": {
					"rotation": {
						"0.0": {
							"vector": [0, 0, 0]
						},
						"0.0833": {
							"vector": [22.5, 0, 0]
						},
						"0.75": {
							"vector": [-5, 0, 0]
						}
					},
					"position": {
						"0.0": {
							"vector": [0, 0, 0]
						},
						"0.0833": {
							"vector": [0, 0, -4]
						},
						"0.75": {
							"vector": [0, 0, -3]
						}
					}
				},
				"right_arm": {
					"rotation": {
						"0.0": {
							"vector": [-90, -5, 5]
						},
						"0.75": {
							"vector": [89.99999, -85, -174.99999]
						}
					},
					"position": {
						"0.0": {
							"vector": [0, 0, 0]
						},
						"0.0833": {
							"vector": [0, -1, -5]
						},
						"0.75": {
							"vector": [0, -3, -3]
						}
					}
				},
				"right_leg": {
					"rotation": {
						"0.0": {
							"vector": [-10, 10, 5]
						},
						"0.0833": {
							"vector": [-32.5, 10, 5]
						},
						"0.1667": {
							"vector": [-35, 10, 5]
						},
						"0.25": {
							"vector": [-25, 10, 5]
						},
						"0.5": {
							"vector": [5, 10, 5]
						}
					},
					"position": {
						"0.0": {
							"vector": [0, 0.25, 0]
						},
						"0.75": {
							"vector": [0, 0.25, -4]
						}
					}
				},
				"left_leg": {
					"rotation": {
						"0.0": {
							"vector": [-10, -10, -5]
						},
						"0.0833": {
							"vector": [-31.66667, -10, -5]
						},
						"0.1667": {
							"vector": [-33.33333, -10, -5]
						},
						"0.25": {
							"vector": [-22.5, -10, -5]
						},
						"0.5": {
							"vector": [5, -10, -5]
						}
					},
					"position": {
						"0.0": {
							"vector": [0, 0.25, 0]
						},
						"0.75": {
							"vector": [0, 0.25, -4]
						}
					}
				},
				"left_arm": {
					"rotation": {
						"0.0": {
							"vector": [-90, 5, -5]
						},
						"0.75": {
							"vector": [89.99999, 85, 174.99999]
						}
					},
					"position": {
						"0.0": {
							"vector": [0, 0, 0]
						},
						"0.0833": {
							"vector": [0, -1, -5]
						},
						"0.75": {
							"vector": [0, -3, -3]
						}
					}
				}
			}
		},
		"kick_right": {
			"animation_length": 0.5,
			"bones": {
				"body": {
					"rotation": {
						"0.0": {
							"vector": [32.94581, 72.03614, 34.26563]
						},
						"0.0417": {
							"vector": [-5.22972, 5.98318, 27.73757]
						},
						"0.0833": {
							"vector": [-61.35598, -50.89407, 73.60068]
						}
					},
					"position": {
						"0.0": {
							"vector": [2, -4, 0]
						},
						"0.0833": {
							"vector": [-2.67, -1.67, -8.67]
						},
						"0.5": {
							"vector": [-2.67, -6.67, -8.67]
						}
					}
				},
				"head": {
					"rotation": {
						"0.0": {
							"vector": [0, -60, 0]
						},
						"0.0833": {
							"vector": [48.30556, 37.29431, 17.15226]
						}
					},
					"position": {
						"0.0": {
							"vector": [0, 0, 0]
						},
						"0.0833": {
							"vector": [-0.42701, 1.05624, -0.83786]
						}
					}
				},
				"torso": {
					"rotation": {
						"vector": [0, 0, 0]
					}
				},
				"right_arm": {
					"rotation": {
						"0.0": {
							"vector": [-65.53631, -0.41163, -56.17316]
						},
						"0.0833": {
							"vector": [-14.7049, -6.95885, -68.71699]
						},
						"0.5": {
							"vector": [-52.2049, -6.95885, -68.71699]
						}
					},
					"position": {
						"vector": [0, 0, 0]
					}
				},
				"right_leg": {
					"rotation": {
						"0.0": {
							"vector": [-18.16551, -25.77885, 56.19913]
						},
						"0.0833": {
							"vector": [-90.17414, 75.40843, -42.3467]
						}
					},
					"position": {
						"0.0": {
							"vector": [0, 0, 0]
						},
						"0.0833": {
							"vector": [1.90692, -5.14848, 1.96388]
						}
					}
				},
				"left_leg": {
					"rotation": {
						"0.0": {
							"vector": [-33.07499, -34.41424, -12.45627]
						},
						"0.0417": {
							"vector": [-15.68605, -23.27978, -27.50974]
						},
						"0.0833": {
							"vector": [-47.94973, -14.51092, -33.65158]
						},
						"0.5": {
							"vector": [-62.94973, -14.51092, -33.65158]
						}
					},
					"position": {
						"0.0": {
							"vector": [0, 0, 0]
						},
						"0.0833": {
							"vector": [-1.11856, -1.20524, 2.50923]
						}
					}
				},
				"left_arm": {
					"rotation": {
						"0.0": {
							"vector": [8.6822, -4.98093, 74.62165]
						},
						"0.0833": {
							"vector": [64.35095, -16.35567, 42.27169]
						},
						"0.5": {
							"vector": [58.38892, 12.01797, 28.919]
						}
					},
					"position": {
						"vector": [0, 0, 0]
					}
				},
				"right_leg2": {
					"rotation": {
						"0.0": {
							"vector": [77.5, 0, 0]
						},
						"0.0833": {
							"vector": [19.87236, 0.93152, -1.21628]
						},
						"0.5": {
							"vector": [10.60055, -2.19599, 0.9586]
						}
					}
				},
				"right_arm2": {
					"rotation": {
						"0.0": {
							"vector": [-35, 0, 0]
						},
						"0.0833": {
							"vector": [-27.5, 0, 0]
						}
					}
				},
				"left_arm2": {
					"rotation": {
						"0.0": {
							"vector": [0, 0, 0]
						},
						"0.0833": {
							"vector": [0, 0, 0]
						}
					}
				},
				"left_leg2": {
					"rotation": {
						"0.0": {
							"vector": [57.5, 0, 0]
						},
						"0.0833": {
							"vector": [50, 0, 0]
						},
						"0.5": {
							"vector": [85, 0, 0]
						}
					}
				},
				"left_leg3": {
					"rotation": {
						"0.0": {
							"vector": [0, 0, 0]
						},
						"0.5": {
							"vector": [-17.5, 0, 0]
						}
					}
				}
			}
		},
		"kick_left": {
			"animation_length": 0.5,
			"bones": {
				"body": {
					"rotation": {
						"0.0": {
							"vector": [32.94581, -72.03614, -34.26563]
						},
						"0.0417": {
							"vector": [-5.22972, -5.98318, -27.73757]
						},
						"0.0833": {
							"vector": [-61.35598, 50.89407, -73.60068]
						}
					},
					"position": {
						"0.0": {
							"vector": [-2, -4, 0]
						},
						"0.0833": {
							"vector": [2.67, -1.67, -8.67]
						},
						"0.5": {
							"vector": [2.67, -6.67, -8.67]
						}
					}
				},
				"head": {
					"rotation": {
						"0.0": {
							"vector": [0, 60, 0]
						},
						"0.0833": {
							"vector": [48.30556, -37.29431, -17.15226]
						}
					},
					"position": {
						"0.0": {
							"vector": [0, 0, 0]
						},
						"0.0833": {
							"vector": [0.42701, 1.05624, -0.83786]
						}
					}
				},
				"torso": {
					"rotation": {
						"vector": [0, 0, 0]
					}
				},
				"right_arm": {
					"rotation": {
						"0.0": {
							"vector": [8.6822, 4.98093, -74.62165]
						},
						"0.0833": {
							"vector": [64.35095, 16.35567, -42.27169]
						},
						"0.5": {
							"vector": [58.38892, -12.01797, -28.919]
						}
					},
					"position": {
						"vector": [0, 0, 0]
					}
				},
				"right_leg": {
					"rotation": {
						"0.0": {
							"vector": [-33.07499, 34.41424, 12.45627]
						},
						"0.0833": {
							"vector": [-47.94973, 14.51092, 33.65158]
						},
						"0.5": {
							"vector": [-62.94973, 14.51092, 33.65158]
						}
					},
					"position": {
						"0.0": {
							"vector": [0, 0, 0]
						},
						"0.0833": {
							"vector": [1.11856, -1.20524, 2.50923]
						}
					}
				},
				"left_leg": {
					"rotation": {
						"0.0": {
							"vector": [-18.16551, 25.77885, -56.19913]
						},
						"0.0417": {
							"vector": [-15.68605, -23.27978, -27.50974]
						},
						"0.0833": {
							"vector": [-90.17414, -75.40843, 42.3467]
						}
					},
					"position": {
						"0.0": {
							"vector": [0, 0, 0]
						},
						"0.0833": {
							"vector": [-1.90692, -5.14848, 1.96388]
						}
					}
				},
				"left_arm": {
					"rotation": {
						"0.0": {
							"vector": [-65.53631, 0.41163, 56.17316]
						},
						"0.0833": {
							"vector": [-14.7049, 6.95885, 68.71699]
						},
						"0.5": {
							"vector": [-52.2049, 6.95885, 68.71699]
						}
					},
					"position": {
						"vector": [0, 0, 0]
					}
				},
				"right_leg2": {
					"rotation": {
						"0.0": {
							"vector": [57.5, 0, 0]
						},
						"0.0833": {
							"vector": [50, 0, 0]
						},
						"0.5": {
							"vector": [85, 0, 0]
						}
					}
				},
				"right_arm2": {
					"rotation": {
						"0.0": {
							"vector": [0, 0, 0]
						},
						"0.0833": {
							"vector": [0, 0, 0]
						}
					}
				},
				"left_arm2": {
					"rotation": {
						"0.0": {
							"vector": [-35, 0, 0]
						},
						"0.0833": {
							"vector": [-27.5, 0, 0]
						}
					}
				},
				"left_leg2": {
					"rotation": {
						"0.0": {
							"vector": [77.5, 0, 0]
						},
						"0.0833": {
							"vector": [19.87236, -0.93152, 1.21628]
						},
						"0.5": {
							"vector": [10.60055, 2.19599, -0.9586]
						}
					}
				},
				"right_leg3": {
					"rotation": {
						"0.0": {
							"vector": [0, 0, 0]
						},
						"0.5": {
							"vector": [-17.5, 0, 0]
						}
					}
				},
				"left_leg3": {
					"rotation": {
						"0.0": {
							"vector": [0, 0, 0]
						},
						"0.5": {
							"vector": [-17.5, 0, 0]
						}
					}
				}
			}
		},
		"punch_right": {
			"animation_length": 0.5,
			"bones": {
				"body": {
					"rotation": {
						"0.0": {
							"vector": [-13.76772, 56.7385, -11.57881]
						},
						"0.0833": {
							"vector": [54.73561, -30, -35.26439]
						},
						"0.5": {
							"vector": [45.72358, -17.45461, -31.60995]
						}
					},
					"position": {
						"0.0": {
							"vector": [0, -8, 0]
						},
						"0.0833": {
							"vector": [0, -5.5, 0]
						}
					}
				},
				"head": {
					"rotation": {
						"0.0": {
							"vector": [0, -35, 0]
						},
						"0.0833": {
							"vector": [0, 30, 0]
						},
						"0.5": {
							"vector": [5.72511, 29.4987, 11.50839]
						}
					}
				},
				"torso": {
					"rotation": {
						"0.0": {
							"vector": [0, 0, 0]
						},
						"0.0833": {
							"vector": [0, -30, 0]
						}
					},
					"position": {
						"vector": [0, 0, 0]
					}
				},
				"right_arm": {
					"rotation": {
						"0.0": {
							"vector": [-97.63627, -20.04444, 14.30983]
						},
						"0.0833": {
							"vector": [67.19043, -21.12119, -108.54367]
						},
						"0.5": {
							"vector": [34.69043, -21.12119, -108.54367]
						}
					},
					"position": {
						"0.0": {
							"vector": [0, -2, 2]
						},
						"0.0833": {
							"vector": [-2.41421, 0, 3]
						}
					}
				},
				"right_leg": {
					"rotation": {
						"0.0": {
							"vector": [22.5, -22.5, 0]
						},
						"0.0833": {
							"vector": [-4.71626, 46.39719, -7.91209]
						},
						"0.5": {
							"vector": [3.34604, 34.80419, 5.16998]
						}
					},
					"position": {
						"0.0": {
							"vector": [-0.38268, 0, 0.92388]
						},
						"0.0833": {
							"vector": [1.38711, -3.87, 1.45289]
						}
					}
				},
				"left_leg": {
					"rotation": {
						"0.0": {
							"vector": [-53.86438, -64.4603, 0.57299]
						},
						"0.0833": {
							"vector": [-85.87985, 34.72993, 43.26402]
						},
						"0.5": {
							"vector": [-86.17571, 23.91321, 49.39893]
						}
					},
					"position": {
						"0.0": {
							"vector": [0, -2, 0]
						},
						"0.0833": {
							"vector": [-3.60421, -1.37, -0.77579]
						}
					}
				},
				"left_arm": {
					"rotation": {
						"0.0": {
							"vector": [59.37183, 68.8564, 168.15722]
						},
						"0.0833": {
							"vector": [-90, 42.5, 0]
						},
						"0.5": {
							"vector": [-90, 20, 0]
						}
					},
					"position": {
						"0.0": {
							"vector": [0, -2, 1]
						},
						"0.0833": {
							"vector": [-0.12132, -3, -4.70711]
						}
					}
				},
				"right_arm2": {
					"rotation": {
						"0.0": {
							"vector": [14.70516, 34.89321, 59.64445]
						},
						"0.0833": {
							"vector": [-48.35297, 52.1323, 5.68829]
						}
					}
				},
				"left_arm2": {
					"rotation": {
						"0.0": {
							"vector": [0, 0, -112.5]
						},
						"0.0833": {
							"vector": [13.2161, 6.328, -23.4398]
						}
					}
				},
				"itemMainHand": {
					"scale": {
						"vector": [0, 0, 0]
					}
				},
				"right_leg2": {
					"rotation": {
						"0.0": {
							"vector": [49.82482, 0.59788, 3.38278]
						},
						"0.0833": {
							"vector": [34.591, 1.20513, 1.93934]
						}
					}
				},
				"left_leg2": {
					"rotation": {
						"0.0": {
							"vector": [68.13565, 4.9951, 12.49774]
						},
						"0.0833": {
							"vector": [66.44028, 20.04892, 1.63851]
						}
					}
				}
			}
		},
		"punch_left": {
			"animation_length": 0.5,
			"bones": {
				"body": {
					"rotation": {
						"0.0": {
							"vector": [-13.76772, -56.7385, 11.57881]
						},
						"0.0833": {
							"vector": [54.73561, 30, 35.26439]
						},
						"0.5": {
							"vector": [45.72358, 17.45461, 31.60995]
						}
					},
					"position": {
						"0.0": {
							"vector": [0, -8, 0]
						},
						"0.0833": {
							"vector": [0, -5.5, 0]
						}
					}
				},
				"head": {
					"rotation": {
						"0.0": {
							"vector": [0, 35, 0]
						},
						"0.0833": {
							"vector": [0, -30, 0]
						},
						"0.5": {
							"vector": [5.72511, -29.4987, -11.50839]
						}
					}
				},
				"torso": {
					"rotation": {
						"0.0": {
							"vector": [0, 0, 0]
						},
						"0.0833": {
							"vector": [0, 30, 0]
						}
					},
					"position": {
						"vector": [0, 0, 0]
					}
				},
				"right_arm": {
					"rotation": {
						"0.0": {
							"vector": [59.37183, -68.8564, -168.15722]
						},
						"0.0833": {
							"vector": [-90, -42.5, 0]
						},
						"0.5": {
							"vector": [-90, -20, 0]
						}
					},
					"position": {
						"0.0": {
							"vector": [0, -2, 1]
						},
						"0.0833": {
							"vector": [0.12132, -3, -4.70711]
						}
					}
				},
				"right_leg": {
					"rotation": {
						"0.0": {
							"vector": [-53.86438, 64.4603, -0.57299]
						},
						"0.0833": {
							"vector": [-85.87985, -34.72993, -43.26402]
						},
						"0.5": {
							"vector": [-86.17571, -23.91321, -49.39893]
						}
					},
					"position": {
						"0.0": {
							"vector": [0, -2, 0]
						},
						"0.0833": {
							"vector": [3.60421, -1.37, -0.77579]
						}
					}
				},
				"left_leg": {
					"rotation": {
						"0.0": {
							"vector": [22.5, 22.5, 0]
						},
						"0.0833": {
							"vector": [-4.71626, -46.39719, 7.91209]
						},
						"0.5": {
							"vector": [3.34604, -34.80419, -5.16998]
						}
					},
					"position": {
						"0.0": {
							"vector": [0.38268, 0, 0.92388]
						},
						"0.0833": {
							"vector": [-1.38711, -3.87, 1.45289]
						}
					}
				},
				"left_arm": {
					"rotation": {
						"0.0": {
							"vector": [-97.63627, 20.04444, -14.30983]
						},
						"0.0833": {
							"vector": [67.19043, 21.12119, 108.54367]
						},
						"0.5": {
							"vector": [34.69043, 21.12119, 108.54367]
						}
					},
					"position": {
						"0.0": {
							"vector": [0, -2, 2]
						},
						"0.0833": {
							"vector": [2.41421, 0, 3]
						}
					}
				},
				"right_arm2": {
					"rotation": {
						"0.0": {
							"vector": [0, 0, 112.5]
						},
						"0.0833": {
							"vector": [13.2161, -6.328, 23.4398]
						}
					}
				},
				"left_arm2": {
					"rotation": {
						"0.0": {
							"vector": [14.70516, -34.89321, -59.64445]
						},
						"0.0833": {
							"vector": [-48.35297, -52.1323, -5.68829]
						}
					}
				},
				"itemMainHand": {
					"scale": {
						"vector": [0, 0, 0]
					}
				},
				"right_leg2": {
					"rotation": {
						"0.0": {
							"vector": [68.13565, -4.9951, -12.49774]
						},
						"0.0833": {
							"vector": [66.44028, -20.04892, -1.63851]
						}
					}
				},
				"left_leg2": {
					"rotation": {
						"0.0": {
							"vector": [49.82482, -0.59788, -3.38278]
						},
						"0.0833": {
							"vector": [34.591, -1.20513, -1.93934]
						}
					}
				}
			}
		},
		"backstep": {
			"animation_length": 0.5,
			"bones": {
				"body": {
					"rotation": {
						"0.0": {
							"vector": [0, 0, 0]
						},
						"0.125": {
							"vector": [-15, 0, 0]
						},
						"0.2917": {
							"vector": [-15, 0, 0]
						},
						"0.5": {
							"vector": [0, 0, 0]
						}
					}
				},
				"torso": {
					"rotation": {
						"0.0": {
							"vector": [0, 0, 0]
						},
						"0.125": {
							"vector": [0, 12.5, 0]
						},
						"0.2917": {
							"vector": [0, 12.5, 0]
						},
						"0.5": {
							"vector": [0, 0, 0]
						}
					}
				},
				"right_wing": {
					"rotation": {
						"0.0": {
							"vector": [0, 75, 0]
						},
						"0.125": {
							"vector": [0, -32.5, 0]
						},
						"0.2917": {
							"vector": [0, -32.5, 0]
						},
						"0.5": {
							"vector": [0, 32.5, 0]
						}
					}
				},
				"left_wing": {
					"rotation": {
						"0.0": {
							"vector": [0, -77.5, 0]
						},
						"0.125": {
							"vector": [0, 32.5, 0]
						},
						"0.2917": {
							"vector": [0, 32.5, 0]
						},
						"0.5": {
							"vector": [0, -32.5, 0]
						}
					}
				},
				"right_arm": {
					"rotation": {
						"0.0": {
							"vector": [0, 0, 0]
						},
						"0.125": {
							"vector": [45, 0, 0]
						},
						"0.2917": {
							"vector": [45, 0, 0]
						},
						"0.5": {
							"vector": [0, 0, 0]
						}
					}
				},
				"left_arm": {
					"rotation": {
						"0.0": {
							"vector": [0, 0, 0]
						},
						"0.125": {
							"vector": [52.5, 0, 0]
						},
						"0.2917": {
							"vector": [52.5, 0, 0]
						},
						"0.5": {
							"vector": [0, 0, 0]
						}
					}
				},
				"right_leg": {
					"rotation": {
						"0.0": {
							"vector": [0, 0, 0]
						},
						"0.125": {
							"vector": [0, 0, 0]
						},
						"0.2917": {
							"vector": [0, 0, 0]
						},
						"0.5": {
							"vector": [0, 0, 0]
						}
					}
				},
				"right_leg2": {
					"rotation": {
						"0.0": {
							"vector": [0, 0, 0]
						},
						"0.125": {
							"vector": [-5, 0, 0]
						},
						"0.2917": {
							"vector": [-5, 0, 0]
						},
						"0.4167": {
							"vector": [0, 0, 0]
						}
					}
				},
				"left_leg": {
					"rotation": {
						"0.0": {
							"vector": [0, 0, 0]
						},
						"0.125": {
							"vector": [-48.26904, 0.70648, 6.78377]
						},
						"0.2917": {
							"vector": [-48.26904, 0.70648, 6.78377]
						},
						"0.5": {
							"vector": [0, 0, 0]
						}
					}
				},
				"right_arm2": {
					"rotation": {
						"0.0": {
							"vector": [0, 0, 0]
						},
						"0.125": {
							"vector": [-87.5, 0, 0]
						},
						"0.2917": {
							"vector": [-87.5, 0, 0]
						},
						"0.5": {
							"vector": [-22.5, 0, 0]
						}
					}
				},
				"left_arm2": {
					"rotation": {
						"0.0": {
							"vector": [0, 0, 0]
						},
						"0.125": {
							"vector": [-105, 0, 0]
						},
						"0.2917": {
							"vector": [-105, 0, 0]
						},
						"0.5": {
							"vector": [-20, 0, 0]
						}
					}
				},
				"head": {
					"rotation": {
						"0.0": {
							"vector": [5.12094, -0.87655, -0.61729]
						},
						"0.125": {
							"vector": [20, 0, 0]
						},
						"0.5": {
							"vector": [0, 0, 0]
						}
					}
				}
			}
		},
		"guard": {
			"animation_length": 0.5,
			"bones": {
				"body": {
					"rotation": {
						"0.125": {
							"vector": [20, 0, 0]
						},
						"0.375": {
							"vector": [20, 0, 0]
						}
					},
					"position": {
						"0.125": {
							"vector": [0, -2, 0]
						},
						"0.375": {
							"vector": [0, -2, 0]
						}
					}
				},
				"head": {
					"position": {
						"0.125": {
							"vector": [0, -3, -4]
						},
						"0.375": {
							"vector": [0, -3, -4]
						}
					}
				},
				"torso": {
					"rotation": {
						"0.125": {
							"vector": [10, 0, 0]
						},
						"0.375": {
							"vector": [10, 0, 0]
						}
					},
					"position": {
						"0.125": {
							"vector": [0, -2, -4]
						},
						"0.375": {
							"vector": [0, -2, -4]
						}
					}
				},
				"right_arm": {
					"rotation": {
						"0.125": {
							"vector": [-74.38521, -49.64442, -34.42036]
						},
						"0.375": {
							"vector": [-74.38521, -49.64442, -34.42036]
						}
					},
					"position": {
						"0.125": {
							"vector": [0, -3, -3]
						},
						"0.375": {
							"vector": [0, -3, -3]
						}
					}
				},
				"left_arm": {
					"rotation": {
						"0.125": {
							"vector": [-35.01116, 30.56196, 14.49587]
						},
						"0.375": {
							"vector": [-35.01116, 30.56196, 14.49587]
						}
					},
					"position": {
						"0.125": {
							"vector": [-1, -4.5, -2]
						},
						"0.375": {
							"vector": [-1, -4.5, -2]
						}
					}
				},
				"right_leg": {
					"rotation": {
						"0.125": {
							"vector": [-72.5, 0, 0]
						},
						"0.375": {
							"vector": [-72.5, 0, 0]
						}
					},
					"position": {
						"0.125": {
							"vector": [0, -3, -2]
						},
						"0.375": {
							"vector": [0, -3, -2]
						}
					}
				},
				"left_leg": {
					"rotation": {
						"0.125": {
							"vector": [15, 0, 0]
						},
						"0.375": {
							"vector": [15, 0, 0]
						}
					},
					"position": {
						"0.125": {
							"vector": [0, 0, 0]
						},
						"0.375": {
							"vector": [0, 0, 0]
						}
					}
				},
				"right_arm2": {
					"rotation": {
						"0.125": {
							"vector": [9.02909, 48.4076, 51.96375]
						},
						"0.375": {
							"vector": [9.02909, 48.4076, 51.96375]
						}
					}
				},
				"left_arm2": {
					"rotation": {
						"0.125": {
							"vector": [-58.03834, -36.27368, 43.65769]
						},
						"0.375": {
							"vector": [-58.03834, -36.27368, 43.65769]
						}
					}
				},
				"right_leg2": {
					"rotation": {
						"0.125": {
							"vector": [42.5, 0, 0]
						},
						"0.375": {
							"vector": [42.5, 0, 0]
						}
					}
				},
				"bone7": {
					"rotation": {
						"0.125": {
							"vector": [0, -40, -97.5]
						},
						"0.375": {
							"vector": [0, -40, -97.5]
						}
					}
				},
				"left_leg2": {
					"rotation": {
						"0.125": {
							"vector": [15, 0, 0]
						},
						"0.375": {
							"vector": [15, 0, 0]
						}
					}
				}
			}
		},
		"both_arm_front": {
			"loop": "hold_on_last_frame",
			"animation_length": 0.48,
			"bones": {
				"body": {
					"position": {
						"vector": [0, -1, -7]
					}
				},
				"head": {
					"position": {
						"vector": [0, 0, -2]
					}
				},
				"torso": {
					"rotation": {
						"vector": [22.5, 0, 0]
					},
					"position": {
						"vector": [0, 0, -2]
					}
				},
				"right_arm": {
					"rotation": {
						"vector": [-65.85133, 20.70481, 9.00717]
					}
				},
				"right_arm2": {
					"rotation": {
						"vector": [-20.94102, -8.42106, 1.55898]
					}
				},
				"left_arm": {
					"rotation": {
						"vector": [-90, -22.5, 0]
					}
				},
				"left_arm2": {
					"rotation": {
						"vector": [22.5, 0, 0]
					}
				},
				"bone4": {
					"rotation": {
						"vector": [0, 0, 22.5]
					}
				},
				"right_leg": {
					"rotation": {
						"vector": [-22.5, 0, 0]
					},
					"position": {
						"vector": [0, 0, 7]
					}
				},
				"right_leg2": {
					"rotation": {
						"vector": [22.5, 0, 0]
					}
				},
				"left_leg": {
					"rotation": {
						"vector": [22.5, 0, 0]
					},
					"position": {
						"vector": [0, 0, 7]
					}
				},
				"left_leg2": {
					"rotation": {
						"vector": [22.5, 0, 0]
					}
				}
			}
		},
		"ragnaraku2": {
			"loop": true,
			"animation_length": 0.75,
			"bones": {
				"body": {
					"rotation": {
						"vector": [50.67731, 23.92746, 26.341]
					},
					"position": {
						"vector": [0, -3, 0]
					}
				},
				"head": {
					"rotation": {
						"vector": [0, 0, 0]
					},
					"position": {
						"vector": [0, 0, 4]
					}
				},
				"torso": {
					"rotation": {
						"vector": [-7.29819, 14.92276, -1.73932]
					},
					"position": {
						"vector": [0, 0, 4]
					}
				},
				"right_arm": {
					"rotation": {
						"vector": [-88.30599, -2.21786, 19.08045]
					},
					"position": {
						"vector": [-0.00016, -3.93266, 4.95199]
					}
				},
				"right_arm2": {
					"rotation": {
						"vector": [0, 0, 70]
					}
				},
				"left_arm": {
					"rotation": {
						"vector": [0.00001, 72.5, 75.00001]
					},
					"position": {
						"vector": [0.3456, -0.34097, 3.67173]
					}
				},
				"left_arm2": {
					"rotation": {
						"vector": [0, 0, -55]
					}
				},
				"right_leg": {
					"rotation": {
						"vector": [-100.23357, -19.92194, 1.7896]
					},
					"position": {
						"vector": [-1.5, 1.17051, 0.09477]
					}
				},
				"right_leg2": {
					"rotation": {
						"vector": [62.5, 0, 0]
					}
				},
				"left_leg": {
					"rotation": {
						"vector": [-2.07018, -33.03685, 6.23407]
					},
					"position": {
						"vector": [0.5, 0.37663, 0.17426]
					}
				},
				"left_leg2": {
					"rotation": {
						"vector": [17.5, 0, 0]
					}
				}
			}
		},
		"walk": {
			"loop": true,
			"animation_length": 4,
			"bones": {
				"belt": {
					"rotation": {
						"vector": ["-20-math.abs(Math.sin(query.anim_time*270))*55", 0, 0]
					}
				},
				"body": {
					"rotation": {
						"vector": ["12.5+Math.sin(query.anim_time*180)*1", "Math.sin(query.anim_time*270)*2", "Math.sin(query.anim_time*270)*1"]
					},
					"position": {
						"vector": [0, "-1+Math.cos(query.anim_time*540)*0.5", 0]
					}
				},
				"right_arm": {
					"rotation": {
						"vector": ["5.6496+Math.sin(query.anim_time*270)*22.5", 0.88554, -14.99063]
					}
				},
				"right_arm2": {
					"rotation": {
						"vector": [-10, 0, 0]
					}
				},
				"left_arm": {
					"rotation": {
						"vector": ["5.6496+Math.sin(query.anim_time*270)*-22.5", -0.88554, 14.99063]
					}
				},
				"left_arm2": {
					"rotation": {
						"vector": [-10, 0, 0]
					}
				},
				"right_leg": {
					"rotation": {
						"vector": ["-25.1797+Math.sin(query.anim_time*270)*40", 4.52874, -2.12723]
					},
					"position": {
						"vector": [0, -0.43288, 1.95259]
					}
				},
				"right_leg2": {
					"rotation": {
						"vector": ["20+Math.sin(query.anim_time*270)*-20", 0, 0]
					}
				},
				"left_leg": {
					"rotation": {
						"vector": ["-25.1797+Math.sin(query.anim_time*270)*-40", -4.52874, 2.12723]
					},
					"position": {
						"vector": [0, -0.43288, 1.95259]
					}
				},
				"left_leg2": {
					"rotation": {
						"vector": ["20+Math.sin(query.anim_time*270)*20", 0, 0]
					}
				},
				"head": {
					"rotation": {
						"vector": [-2.5, 0, 0]
					}
				}
			}
		},
		"sword_to_left": {
			"animation_length": 0.5,
			"bones": {
				"body": {
					"rotation": {
						"0.0": {
							"vector": [20, 40, 0]
						},
						"0.0833": {
							"vector": [113.76613, -77.01894, -86.23387]
						},
						"0.5": {
							"vector": [58.08525, -65.59281, -32.84949]
						}
					},
					"position": {
						"0.0": {
							"vector": [0, -8, 0]
						},
						"0.5": {
							"vector": [0, -7, 0]
						}
					}
				},
				"head": {
					"rotation": {
						"0.0": {
							"vector": [-7.23631, -41.64114, 18.88172]
						},
						"0.0833": {
							"vector": [-32.93815, 76.62897, -48.09717]
						}
					}
				},
				"torso": {
					"rotation": {
						"0.0": {
							"vector": [0, 0, 0]
						},
						"0.0833": {
							"vector": [10, 0, 0]
						}
					},
					"position": {
						"0.0": {
							"vector": [0, 0, 0]
						},
						"0.0833": {
							"vector": [0, -1, 0]
						}
					}
				},
				"right_arm": {
					"rotation": {
						"0.0": {
							"vector": [-64.10367, -23.2886, -10.97412]
						},
						"0.0833": {
							"vector": [-101.82308, -75.27535, 28.71786]
						},
						"0.5": {
							"vector": [-147.20672, -86.4482, 74.4292]
						}
					},
					"position": {
						"vector": [0, 0, 0]
					}
				},
				"left_arm": {
					"rotation": {
						"0.0": {
							"vector": [-207.94698, 20.60195, -70.86376]
						},
						"0.0833": {
							"vector": [-79.19012, -27.06007, -18.1995]
						},
						"0.5": {
							"vector": [-62.06457, -41.74522, -21.92977]
						}
					},
					"position": {
						"0.0": {
							"vector": [0, 0, 0]
						},
						"0.0833": {
							"vector": [-3, -2, -1]
						}
					}
				},
				"right_leg": {
					"rotation": {
						"0.0": {
							"vector": [6.71535, -34.153, 24.44857]
						},
						"0.0833": {
							"vector": [-27.75446, 54.08684, -37.47884]
						}
					},
					"position": {
						"0.0": {
							"vector": [0, 0, 0]
						},
						"0.0833": {
							"vector": [1, -2.36958, 6.51038]
						}
					}
				},
				"left_leg": {
					"rotation": {
						"0.0": {
							"vector": [-88.20279, -44.58231, 25.78436]
						},
						"0.0833": {
							"vector": [-118.01578, 57.965, -37.28135]
						},
						"0.5": {
							"vector": [-97.9848, 51.05956, -13.22258]
						}
					},
					"position": {
						"0.0": {
							"vector": [0, 0, 0]
						},
						"0.0833": {
							"vector": [0, 0, 0]
						}
					}
				},
				"left_arm2": {
					"rotation": {
						"0.0": {
							"vector": [0, 0, 0]
						},
						"0.0833": {
							"vector": [167.34839, 81.03833, 109.60181]
						},
						"0.5": {
							"vector": [254.03724, 74.91717, 247.10003]
						}
					}
				},
				"right_arm2": {
					"rotation": {
						"0.0": {
							"vector": [-0.1356, 21.34949, 50.96203]
						},
						"0.0833": {
							"vector": [4.91309, 29.20676, 73.73043]
						},
						"0.5": {
							"vector": [18.88516, 16.68997, 52.00165]
						}
					}
				},
				"right_leg2": {
					"rotation": {
						"0.0": {
							"vector": [24.74147, 3.68189, 1.20689]
						},
						"0.0833": {
							"vector": [49.62715, 4.40287, 0.08217]
						}
					}
				},
				"left_leg2": {
					"rotation": {
						"0.0": {
							"vector": [64.97215, 0.1368, -1.20885]
						},
						"0.0833": {
							"vector": [47.44776, 0.58361, -1.97718]
						}
					}
				}
			}
		},
		"sword_to_right": {
			"animation_length": 0.5,
			"bones": {
				"head": {
					"rotation": {
						"0.0": {
							"vector": [0, 0, 0]
						},
						"0.0833": {
							"vector": [-71.40007, -73.34623, 60.95914]
						},
						"0.5": {
							"vector": [-38.56193, -75.35924, 25.6424]
						}
					},
					"position": {
						"vector": [0, -1, 0]
					}
				},
				"torso": {
					"rotation": {
						"0.0": {
							"vector": [37.59117, -74.75245, -32.7431]
						},
						"0.0833": {
							"vector": [12.2638, -37.04866, -5.27575]
						}
					},
					"position": {
						"vector": [0, -1, 0]
					}
				},
				"right_arm": {
					"rotation": {
						"0.0": {
							"vector": [28.16894, -19.36311, -67.45797]
						},
						"0.0833": {
							"vector": [56.70536, -12.4692, -72.72424]
						},
						"0.5": {
							"vector": [53.80389, -24.82139, -63.71822]
						}
					},
					"position": {
						"0.0": {
							"vector": [-8, 0, 9]
						},
						"0.0833": {
							"vector": [-3, -2, 7]
						}
					}
				},
				"left_arm": {
					"rotation": {
						"0.0": {
							"vector": [-206.83949, -27.40337, 122.1566]
						},
						"0.0417": {
							"vector": [-96.37135, -9.40643, 87.64363]
						},
						"0.0833": {
							"vector": [-29.23827, 5.29306, 102.06078]
						},
						"0.5": {
							"vector": [-30.18275, 10.91555, 81.51741]
						}
					},
					"position": {
						"0.0": {
							"vector": [6, -5, -10.26795]
						},
						"0.0833": {
							"vector": [1, -3, -6]
						}
					}
				},
				"right_leg": {
					"rotation": {
						"0.0": {
							"vector": [-92.84072, 25.13398, -16.29403]
						},
						"0.0417": {
							"vector": [-87.71555, -23.64878, -19.00286]
						},
						"0.0833": {
							"vector": [-95.49935, -57.20933, -2.30158]
						},
						"0.5": {
							"vector": [-85.79523, -61.54821, -13.89834]
						}
					},
					"position": {
						"0.0": {
							"vector": [0.6119, -4.26509, 1.3912]
						},
						"0.0833": {
							"vector": [-3.13031, -5.13397, 2.22548]
						}
					}
				},
				"left_leg": {
					"rotation": {
						"0.0": {
							"vector": [4.79124, -8.58515, -1.73654]
						},
						"0.0833": {
							"vector": [-13.20993, -76.02089, 19.06434]
						},
						"0.5": {
							"vector": [14.72313, -67.95571, -15.54241]
						}
					},
					"position": {
						"0.0": {
							"vector": [-2.8, -3.59808, 5.3]
						},
						"0.0833": {
							"vector": [-1.20958, -2.73397, 5.58679]
						}
					}
				},
				"body": {
					"rotation": {
						"0.0": {
							"vector": [30, -32.5, 0]
						},
						"0.0417": {
							"vector": [46.09255, 26.40504, 32.33614]
						},
						"0.0833": {
							"vector": [92.87677, 65.02468, 75.93853]
						},
						"0.5": {
							"vector": [65.85389, 56.77406, 61.81321]
						}
					},
					"position": {
						"0.0": {
							"vector": [0, -5, 0]
						},
						"0.0833": {
							"vector": [-4, -6, -5]
						},
						"0.5": {
							"vector": [-3, -6, -4]
						}
					}
				},
				"right_arm2": {
					"rotation": {
						"0.0": {
							"vector": [-50, 0, 0]
						},
						"0.0833": {
							"vector": [-22.5, 0, 0]
						}
					}
				},
				"right_leg2": {
					"rotation": {
						"0.0": {
							"vector": [67.5, 0, 0]
						},
						"0.0833": {
							"vector": [52.5, 0, 0]
						},
						"0.5": {
							"vector": [55, 0, 0]
						}
					}
				},
				"left_leg2": {
					"rotation": {
						"0.0": {
							"vector": [40, 0, 0]
						},
						"0.0833": {
							"vector": [40, 0, 0]
						},
						"0.5": {
							"vector": [47.43043, 0.57704, -0.80436]
						}
					}
				},
				"left_arm2": {
					"rotation": {
						"0.0": {
							"vector": [-35, 0, 0]
						},
						"0.0833": {
							"vector": [23.15411, 40.11485, 15.40534]
						},
						"0.5": {
							"vector": [0, 0, 0]
						}
					}
				}
			}
		},
		"sword_overhead": {
			"loop": "hold_on_last_frame",
			"animation_length": 0.75,
			"bones": {
				"body": {
					"position": {
						"0.0": {
							"vector": [0, 0, 0]
						},
						"0.125": {
							"vector": [0, -3.2, 0]
						},
						"0.2083": {
							"vector": [0, -3.2, 0]
						}
					}
				},
				"head": {
					"rotation": {
						"0.0": {
							"vector": [0, 0, 0]
						},
						"0.0833": {
							"vector": [0, 0, 0]
						},
						"0.125": {
							"vector": [35, 0, 0]
						}
					},
					"position": {
						"0.0": {
							"vector": [0, 0, 4]
						},
						"0.0417": {
							"vector": [2.57, -0.69, -2.14]
						},
						"0.0833": {
							"vector": [3.93, -1.73, -1.85]
						},
						"0.125": {
							"vector": [5, -4.86, -5]
						},
						"0.2083": {
							"vector": [4, -8.86, -5.5]
						}
					}
				},
				"torso": {
					"rotation": {
						"0.0": {
							"vector": [-7.49644, -19.80357, 2.7023]
						},
						"0.0417": {
							"vector": [16.25534, -29.70536, -3.44655]
						},
						"0.0833": {
							"vector": [18.75534, -29.70536, -3.44655]
						},
						"0.125": {
							"vector": [34.51169, -35.21284, -4.81845]
						},
						"0.2083": {
							"vector": [39.51169, -35.21284, -4.81845]
						}
					},
					"position": {
						"0.0": {
							"vector": [0, 0, 4]
						},
						"0.0417": {
							"vector": [0.59, -0.54, -0.99]
						},
						"0.125": {
							"vector": [2.1, -3.76, -2.9]
						},
						"0.2083": {
							"vector": [2.1, -6.76, -2.9]
						}
					}
				},
				"right_arm": {
					"rotation": {
						"0.0": {
							"vector": [-20, 0, -15]
						},
						"0.0417": {
							"vector": [6.00031, -3.23472, -18.60552]
						},
						"0.0833": {
							"vector": [6.00031, -3.23472, -18.60552]
						},
						"0.125": {
							"vector": [26.70536, -12.4692, -72.72424]
						},
						"0.2083": {
							"vector": [26.28767, -46.22078, -61.87578]
						}
					},
					"position": {
						"0.0": {
							"vector": [0, 0, 7]
						},
						"0.0417": {
							"vector": [-1, -2, 5]
						},
						"0.0833": {
							"vector": [0, -1, 1]
						},
						"0.125": {
							"vector": [-1, -3, 6]
						},
						"0.2083": {
							"vector": [-2, -6, 5]
						}
					}
				},
				"right_arm2": {
					"rotation": {
						"0.0": {
							"vector": [0, 0, 0]
						},
						"0.125": {
							"vector": [15, 0, 0]
						},
						"0.2083": {
							"vector": [25, 0, 0]
						}
					}
				},
				"left_arm": {
					"rotation": {
						"0.0": {
							"vector": [-198.40071, -11.99068, -8.31148]
						},
						"0.0417": {
							"vector": [-150.90071, -11.99068, -8.31148]
						},
						"0.0833": {
							"vector": [-150.90071, -11.99068, -8.31148]
						},
						"0.125": {
							"vector": [-14.07801, -6.15762, -15.6551]
						},
						"0.2083": {
							"vector": [-14.08, -6.16, -15.66]
						}
					},
					"position": {
						"0.0": {
							"vector": [0.84, 1.34, 2]
						},
						"0.0417": {
							"vector": [1, -2, -7]
						},
						"0.0833": {
							"vector": [2, -1, -6]
						},
						"0.125": {
							"vector": [1, -5, -7]
						},
						"0.2083": {
							"vector": [1, -8, -7]
						}
					}
				},
				"left_arm2": {
					"rotation": {
						"0.0": {
							"vector": [0, 0, 0]
						},
						"0.125": {
							"vector": [35, 0, 0]
						},
						"0.2083": {
							"vector": [35, 0, 0]
						}
					}
				},
				"bone4": {
					"rotation": {
						"0.0": {
							"vector": [0, 0, 0]
						},
						"0.125": {
							"vector": [37.5, 0, 0]
						}
					}
				},
				"right_leg": {
					"rotation": {
						"0.0": {
							"vector": [-57.5, 0, 0]
						},
						"0.0417": {
							"vector": [-21.50238, -21.07593, 8.0634]
						},
						"0.0833": {
							"vector": [-21.50238, -21.07593, 8.0634]
						},
						"0.125": {
							"vector": [-55.13886, 0.97251, -0.02452]
						},
						"0.2083": {
							"vector": [-55.13886, 0.97251, -0.02452]
						}
					},
					"position": {
						"0.0": {
							"vector": [-1.5, 0, 0]
						},
						"0.0417": {
							"vector": [-3, -2, 1.2]
						},
						"0.0833": {
							"vector": [0, 0, 1.2]
						},
						"0.125": {
							"vector": [-4.8, -2, 5.2]
						},
						"0.2083": {
							"vector": [-4.8, -2, 5.2]
						}
					}
				},
				"right_leg2": {
					"rotation": {
						"0.0": {
							"vector": [40, 0, 0]
						},
						"0.125": {
							"vector": [49, 0, 0]
						},
						"0.2083": {
							"vector": [49, 0, 0]
						}
					}
				},
				"left_leg": {
					"rotation": {
						"0.0": {
							"vector": [10, 0, 0]
						},
						"0.0417": {
							"vector": [25.56145, -27.51235, -12.45891]
						},
						"0.0833": {
							"vector": [25.56145, -27.51235, -12.45891]
						},
						"0.125": {
							"vector": [27.81179, -9.23186, -3.86032]
						},
						"0.2083": {
							"vector": [27.81, -9.23, -3.86]
						}
					},
					"position": {
						"0.0": {
							"vector": [-0.5, 0.5, 3]
						},
						"0.0417": {
							"vector": [-2.8, 0, 6.8]
						},
						"0.0833": {
							"vector": [-0.8, 0, 2.8]
						},
						"0.125": {
							"vector": [-5.4, -1, 8.3]
						},
						"0.2083": {
							"vector": [-5.4, -1, 8.3]
						}
					}
				},
				"left_leg2": {
					"rotation": {
						"0.0": {
							"vector": [0, 0, 0]
						},
						"0.125": {
							"vector": [22.5, 0, 0]
						},
						"0.2083": {
							"vector": [22.5, 0, 0]
						}
					}
				}
			}
		},
		"punch_overhead": {
			"loop": "hold_on_last_frame",
			"animation_length": 0.75,
			"bones": {
				"body": {
					"position": {
						"0.0": {
							"vector": [0, 0, 0]
						},
						"0.0417": {
							"vector": [0, -5.4, -6.33]
						},
						"0.0833": {
							"vector": [0, -11.8, -12.67]
						},
						"0.125": {
							"vector": [0, -22.2, -19]
						}
					}
				},
				"head": {
					"rotation": {
						"0.0": {
							"vector": [0, 0, 0]
						},
						"0.0833": {
							"vector": [0, 0, 0]
						},
						"0.125": {
							"vector": [35, 0, 0]
						}
					},
					"position": {
						"0.0": {
							"vector": [0, 0, 4]
						},
						"0.0417": {
							"vector": [2.57, -1.69, -2.14]
						},
						"0.0833": {
							"vector": [1.93, -3.73, -2.85]
						},
						"0.125": {
							"vector": [3, -7.86, -5]
						}
					}
				},
				"torso": {
					"rotation": {
						"0.0": {
							"vector": [-7.49644, -19.80357, 2.7023]
						},
						"0.125": {
							"vector": [81.21949, -13.01985, -8.91859]
						}
					},
					"position": {
						"0.0": {
							"vector": [0, 0, 4]
						},
						"0.0417": {
							"vector": [0.59, -0.54, -0.99]
						},
						"0.125": {
							"vector": [2.1, -3.76, -2.9]
						}
					}
				},
				"right_arm": {
					"rotation": {
						"0.0": {
							"vector": [-20, 0, -15]
						},
						"0.0417": {
							"vector": [6.00031, -3.23472, -18.60552]
						},
						"0.0833": {
							"vector": [6.00031, -3.23472, -18.60552]
						},
						"0.125": {
							"vector": [26.70536, -12.4692, -72.72424]
						}
					},
					"position": {
						"0.0": {
							"vector": [0, 0, 7]
						},
						"0.0417": {
							"vector": [-1, -2, 3]
						},
						"0.0833": {
							"vector": [0, -1, 3]
						},
						"0.125": {
							"vector": [2, -1, 3]
						}
					}
				},
				"right_arm2": {
					"rotation": {
						"0.0": {
							"vector": [0, 0, 0]
						},
						"0.125": {
							"vector": [15, 0, 0]
						},
						"0.2083": {
							"vector": [25, 0, 0]
						}
					}
				},
				"left_arm": {
					"rotation": {
						"0.0": {
							"vector": [-198.40071, -11.99068, -8.31148]
						},
						"0.0417": {
							"vector": [-159.45981, -10.04633, -10.75935]
						},
						"0.125": {
							"vector": [-14.07801, -6.15762, -15.6551]
						}
					},
					"position": {
						"0.0": {
							"vector": [0.84, 1.34, 2]
						},
						"0.0417": {
							"vector": [0, -2, -3]
						},
						"0.0833": {
							"vector": [2, -2, 0]
						},
						"0.125": {
							"vector": [1, -2, -1]
						}
					}
				},
				"left_arm2": {
					"rotation": {
						"0.0": {
							"vector": [0, 0, 0]
						},
						"0.0417": {
							"vector": [-55.83, 0, 0]
						},
						"0.125": {
							"vector": [35, 0, 0]
						}
					}
				},
				"bone4": {
					"rotation": {
						"0.0": {
							"vector": [0, 0, 0]
						},
						"0.125": {
							"vector": [37.5, 0, 0]
						}
					}
				},
				"right_leg": {
					"rotation": {
						"0.0": {
							"vector": [-12.5, 0, 0]
						},
						"0.0417": {
							"vector": [-21.50238, -21.07593, 8.0634]
						},
						"0.0833": {
							"vector": [-68.29161, 8.78511, -6.69969]
						},
						"0.125": {
							"vector": [-55.13886, 0.97251, -0.02452]
						}
					},
					"position": {
						"0.0": {
							"vector": [-1.5, 0, 0]
						},
						"0.125": {
							"vector": [-3.8, 15, 18.2]
						}
					}
				},
				"right_leg2": {
					"rotation": {
						"0.0": {
							"vector": [40, 0, 0]
						},
						"0.0833": {
							"vector": [68.98, 0, 0]
						},
						"0.125": {
							"vector": [49, 0, 0]
						},
						"0.2083": {
							"vector": [49, 0, 0]
						}
					}
				},
				"left_leg": {
					"rotation": {
						"0.0": {
							"vector": [10, 0, 0]
						},
						"0.0417": {
							"vector": [25.56145, -27.51235, -12.45891]
						},
						"0.0833": {
							"vector": [25.56145, -27.51235, -12.45891]
						},
						"0.125": {
							"vector": [27.81179, -9.23186, -3.86032]
						}
					},
					"position": {
						"0.0": {
							"vector": [-0.5, 0.5, 3]
						},
						"0.125": {
							"vector": [0.6, 14, 21.3]
						}
					}
				},
				"left_leg2": {
					"rotation": {
						"0.0": {
							"vector": [0, 0, 0]
						},
						"0.125": {
							"vector": [45, 0, 0]
						}
					}
				}
			}
		},
		"fall1": {
			"animation_length": 0.75,
			"bones": {
				"body": {
					"rotation": {
						"0.0": {
							"vector": [22.5, 0, 0]
						},
						"0.0833": {
							"vector": [22.5, 0, 0]
						}
					},
					"position": {
						"0.0": {
							"vector": [0, "-3+math.sin(query.anim_time*180)*1", 2]
						},
						"0.0833": {
							"vector": [0, -9, 5]
						},
						"0.75": {
							"vector": [0, -7, 5]
						}
					}
				},
				"head": {
					"rotation": {
						"0.0": {
							"vector": [-15, 0, 0]
						},
						"0.0833": {
							"vector": [-15, 0, 0]
						}
					},
					"position": {
						"0.0": {
							"vector": [0, -1, -1]
						},
						"0.0833": {
							"vector": [0, -1, -1]
						}
					}
				},
				"torso": {
					"rotation": {
						"vector": [0, 0, 0]
					},
					"position": {
						"vector": [0, 0, 0]
					}
				},
				"right_arm": {
					"rotation": {
						"0.0": {
							"vector": [-29.62165, -4.98093, "-3.6821+math.sin(query.anim_time*180)*5"]
						},
						"0.0833": {
							"vector": [43.37091, 0.30722, "-36.1509+math.sin(query.anim_time*180)*5"]
						}
					},
					"position": {
						"vector": [0, 0, 0]
					}
				},
				"right_arm2": {
					"rotation": {
						"0.0": {
							"vector": [0, 0, 0]
						},
						"0.0833": {
							"vector": [-50, 0, 0]
						}
					}
				},
				"left_arm": {
					"rotation": {
						"0.0": {
							"vector": [-29.40842, 6.21271, "5.868+math.sin(query.anim_time*180)*-5"]
						},
						"0.0833": {
							"vector": [45.87091, -0.30722, "36.1509+math.sin(query.anim_time*180)*-5"]
						}
					},
					"position": {
						"vector": [0, 0, 0]
					}
				},
				"left_arm2": {
					"rotation": {
						"0.0": {
							"vector": [0, 0, 0]
						},
						"0.0833": {
							"vector": [-50, 0, 0]
						}
					}
				},
				"right_leg": {
					"rotation": {
						"0.0": {
							"vector": ["-55+math.sin(query.anim_time*180)*-5", 0, 0]
						},
						"0.0833": {
							"vector": [-102.9264, 14.6364, -3.31913]
						},
						"0.75": {
							"vector": [-92.9264, 14.6364, -3.31913]
						}
					},
					"position": {
						"0.0": {
							"vector": [0, 0, 0]
						},
						"0.0833": {
							"vector": [-1, -5.99162, 4.01254]
						},
						"0.75": {
							"vector": [-1, -5.99162, 4.01254]
						}
					}
				},
				"right_leg2": {
					"rotation": {
						"0.0": {
							"vector": [45, 0, 0]
						},
						"0.0833": {
							"vector": [85, 0, 0]
						},
						"0.75": {
							"vector": [75, 0, 0]
						}
					}
				},
				"left_leg": {
					"rotation": {
						"0.0": {
							"vector": ["-55+math.sin(query.anim_time*180)*-5", 0, 0]
						},
						"0.0833": {
							"vector": [-102.9264, -14.6364, 3.31914]
						},
						"0.75": {
							"vector": [-92.9264, -14.6364, 3.31914]
						}
					},
					"position": {
						"0.0": {
							"vector": [0, 0, 0]
						},
						"0.0833": {
							"vector": [1, -5.99162, 4.01254]
						},
						"0.75": {
							"vector": [1, -5.99162, 4.01254]
						}
					}
				},
				"left_leg2": {
					"rotation": {
						"0.0": {
							"vector": [45, 0, 0]
						},
						"0.0833": {
							"vector": [85, 0, 0]
						},
						"0.75": {
							"vector": [75, 0, 0]
						}
					}
				}
			}
		}
	},
	"geckolib_format_version": 2
}